tpubar/__init__.py
tpubar/_version.py
tpubar/auth.json
tpubar/cli.py
tpubar/host.py
tpubar/monitor.py
tpubar/network.py
tpubar/utils.py
tpubar-0.0.9.dist-info/LICENSE
tpubar-0.0.9.dist-info/METADATA
tpubar-0.0.9.dist-info/WHEEL
tpubar-0.0.9.dist-info/entry_points.txt
tpubar-0.0.9.dist-info/top_level.txt
tpubar-0.0.9.dist-info/RECORD
