Metadata-Version: 2.1
Name: tpubar
Version: 0.0.9
Summary: tpubar
Home-page: http://github.com/trisongz/tpubar
Author: Tri Songz
Author-email: ts@scontentenginex.com
License: UNKNOWN
Keywords: tpu,progress bar,monitoring,google cloud,tensorflow
Platform: UNKNOWN
Classifier: Development Status :: 3 - Alpha
Classifier: Environment :: Console
Classifier: Intended Audience :: Developers
Requires-Python: >3.6
Requires-Dist: tqdm (>=4.50.0)
Requires-Dist: google-cloud-monitoring
Requires-Dist: tensorflow
Requires-Dist: psutil
Requires-Dist: click
Requires-Dist: pysimdjson
Requires-Dist: tpunicorn
